Metadata-Version: 2.1
Name: gamma-coding
Version: 1.0.2
Summary: Python package implementing gamma coding.
Home-page: https://github.com/LucaCappelletti94/gamma_coding
Author: Luca Cappelletti
Author-email: cappelletti.luca94@gmail.com
License: MIT
Platform: UNKNOWN
Classifier: Development Status :: 3 - Alpha
Classifier: License :: OSI Approved :: MIT License
Classifier: Programming Language :: Python :: 3
Provides-Extra: test
